Metadata-Version: 2.1
Name: liteexpr
Version: 0.0.8
Summary: A light, expression language.
Home-page: https://github.com/markuskimius/liteexpr
Author: Mark Kim
Author-email: markuskimius+py@gmail.com
License: Apache 2.0
Keywords: expression,language,antlr4
Provides-Extra: compile
